{
  "annotations": {
    "list": [
      {
        "builtIn": 1,
        "datasource": { "type": "grafana", "uid": "-- Grafana --" },
        "enable": true,
        "hide": true,
        "iconColor": "rgba(0, 211, 255, 1)",
        "name": "Annotations & Alerts",
        "type": "dashboard"
      }
    ]
  },
  "description": "Xergon Network - Agent & Relay monitoring dashboard",
  "editable": true,
  "fiscalYearStartMonth": 0,
  "graphTooltip": 1,
  "id": null,
  "links": [],
  "liveNow": false,
  "panels": [
    {
      "collapsed": false,
      "gridPos": { "h": 1, "w": 24, "x": 0, "y": 0 },
      "id": 1,
      "panels": [],
      "title": "System Overview",
      "type": "row"
    },
    {
      "datasource": { "type": "prometheus", "uid": "${DS_PROMETHEUS}" },
      "fieldConfig": {
        "defaults": {
          "color": { "mode": "thresholds" },
          "thresholds": {
            "mode": "absolute",
            "steps": [
              { "color": "green", "value": null },
              { "color": "red", "value": 0 }
            ]
          },
          "unit": "s"
        },
        "overrides": []
      },
      "gridPos": { "h": 4, "w": 6, "x": 0, "y": 1 },
      "id": 2,
      "options": {
        "colorMode": "background",
        "graphMode": "none",
        "justifyMode": "center",
        "orientation": "auto",
        "reduceOptions": { "calcs": ["lastNotNull"], "fields": "", "values": false },
        "textMode": "auto"
      },
      "targets": [
        {
          "datasource": { "type": "prometheus", "uid": "${DS_PROMETHEUS}" },
          "expr": "xergon_uptime_seconds{job=\"xergon-agent\"}",
          "refId": "A"
        }
      ],
      "title": "Agent Uptime",
      "type": "stat"
    },
    {
      "datasource": { "type": "prometheus", "uid": "${DS_PROMETHEUS}" },
      "fieldConfig": {
        "defaults": {
          "color": { "mode": "thresholds" },
          "thresholds": {
            "mode": "absolute",
            "steps": [
              { "color": "green", "value": null }
            ]
          },
          "unit": "s"
        },
        "overrides": []
      },
      "gridPos": { "h": 4, "w": 6, "x": 6, "y": 1 },
      "id": 3,
      "options": {
        "colorMode": "background",
        "graphMode": "none",
        "justifyMode": "center",
        "orientation": "auto",
        "reduceOptions": { "calcs": ["lastNotNull"], "fields": "", "values": false },
        "textMode": "auto"
      },
      "targets": [
        {
          "datasource": { "type": "prometheus", "uid": "${DS_PROMETHEUS}" },
          "expr": "xergon_relay_uptime_seconds",
          "refId": "A"
        }
      ],
      "title": "Relay Uptime",
      "type": "stat"
    },
    {
      "datasource": { "type": "prometheus", "uid": "${DS_PROMETHEUS}" },
      "fieldConfig": {
        "defaults": {
          "color": { "mode": "thresholds" },
          "mappings": [
            { "options": { "0": { "color": "red", "index": 1, "text": "DOWN" }, "1": { "color": "green", "index": 0, "text": "UP" } }, "type": "value" }
          ],
          "thresholds": {
            "mode": "absolute",
            "steps": [
              { "color": "green", "value": null },
              { "color": "red", "value": 0 }
            ]
          }
        },
        "overrides": []
      },
      "gridPos": { "h": 4, "w": 6, "x": 12, "y": 1 },
      "id": 4,
      "options": {
        "colorMode": "background",
        "graphMode": "none",
        "justifyMode": "center",
        "orientation": "auto",
        "reduceOptions": { "calcs": ["lastNotNull"], "fields": "", "values": false },
        "textMode": "value"
      },
      "targets": [
        {
          "datasource": { "type": "prometheus", "uid": "${DS_PROMETHEUS}" },
          "expr": "up{job=\"xergon-agent\"}",
          "refId": "A"
        }
      ],
      "title": "Agent Status",
      "type": "stat"
    },
    {
      "datasource": { "type": "prometheus", "uid": "${DS_PROMETHEUS}" },
      "fieldConfig": {
        "defaults": {
          "color": { "mode": "thresholds" },
          "mappings": [
            { "options": { "0": { "color": "red", "index": 1, "text": "DOWN" }, "1": { "color": "green", "index": 0, "text": "UP" } }, "type": "value" }
          ],
          "thresholds": {
            "mode": "absolute",
            "steps": [
              { "color": "green", "value": null },
              { "color": "red", "value": 0 }
            ]
          }
        },
        "overrides": []
      },
      "gridPos": { "h": 4, "w": 6, "x": 18, "y": 1 },
      "id": 5,
      "options": {
        "colorMode": "background",
        "graphMode": "none",
        "justifyMode": "center",
        "orientation": "auto",
        "reduceOptions": { "calcs": ["lastNotNull"], "fields": "", "values": false },
        "textMode": "value"
      },
      "targets": [
        {
          "datasource": { "type": "prometheus", "uid": "${DS_PROMETHEUS}" },
          "expr": "up{job=\"xergon-relay\"}",
          "refId": "A"
        }
      ],
      "title": "Relay Status",
      "type": "stat"
    },
    {
      "collapsed": false,
      "gridPos": { "h": 1, "w": 24, "x": 0, "y": 5 },
      "id": 6,
      "panels": [],
      "title": "Inference",
      "type": "row"
    },
    {
      "datasource": { "type": "prometheus", "uid": "${DS_PROMETHEUS}" },
      "fieldConfig": {
        "defaults": {
          "color": { "mode": "palette-classic" },
          "unit": "reqps"
        },
        "overrides": []
      },
      "gridPos": { "h": 8, "w": 6, "x": 0, "y": 6 },
      "id": 7,
      "options": {
        "legend": { "calcs": [], "displayMode": "list", "placement": "bottom" },
        "tooltip": { "mode": "multi", "sort": "none" }
      },
      "targets": [
        {
          "datasource": { "type": "prometheus", "uid": "${DS_PROMETHEUS}" },
          "expr": "rate(xergon_inference_requests_total[5m])",
          "legendFormat": "requests/s",
          "refId": "A"
        }
      ],
      "title": "Inference Requests",
      "type": "timeseries"
    },
    {
      "datasource": { "type": "prometheus", "uid": "${DS_PROMETHEUS}" },
      "fieldConfig": {
        "defaults": {
          "color": { "mode": "palette-classic" },
          "unit": "short"
        },
        "overrides": []
      },
      "gridPos": { "h": 8, "w": 6, "x": 6, "y": 6 },
      "id": 8,
      "options": {
        "legend": { "calcs": [], "displayMode": "list", "placement": "bottom" },
        "tooltip": { "mode": "multi", "sort": "none" }
      },
      "targets": [
        {
          "datasource": { "type": "prometheus", "uid": "${DS_PROMETHEUS}" },
          "expr": "rate(xergon_inference_tokens_total[5m])",
          "legendFormat": "tokens/s",
          "refId": "A"
        }
      ],
      "title": "Inference Tokens",
      "type": "timeseries"
    },
    {
      "datasource": { "type": "prometheus", "uid": "${DS_PROMETHEUS}" },
      "fieldConfig": {
        "defaults": {
          "color": { "mode": "thresholds" },
          "thresholds": {
            "mode": "absolute",
            "steps": [
              { "color": "green", "value": null },
              { "color": "yellow", "value": 10000 },
              { "color": "red", "value": 30000 }
            ]
          },
          "unit": "ms"
        },
        "overrides": []
      },
      "gridPos": { "h": 8, "w": 6, "x": 12, "y": 6 },
      "id": 9,
      "options": {
        "colorMode": "background",
        "graphMode": "area",
        "justifyMode": "center",
        "orientation": "auto",
        "reduceOptions": { "calcs": ["lastNotNull"], "fields": "", "values": false },
        "textMode": "auto"
      },
      "targets": [
        {
          "datasource": { "type": "prometheus", "uid": "${DS_PROMETHEUS}" },
          "expr": "xergon_agent_inference_latency_ms",
          "refId": "A"
        }
      ],
      "title": "Inference Latency",
      "type": "stat"
    },
    {
      "datasource": { "type": "prometheus", "uid": "${DS_PROMETHEUS}" },
      "fieldConfig": {
        "defaults": {
          "color": { "mode": "palette-classic" },
          "unit": "short"
        },
        "overrides": []
      },
      "gridPos": { "h": 8, "w": 6, "x": 18, "y": 6 },
      "id": 10,
      "options": {
        "legend": { "calcs": [], "displayMode": "list", "placement": "bottom" },
        "tooltip": { "mode": "multi", "sort": "none" }
      },
      "targets": [
        {
          "datasource": { "type": "prometheus", "uid": "${DS_PROMETHEUS}" },
          "expr": "rate(xergon_agent_inference_errors_total[5m])",
          "legendFormat": "errors/s",
          "refId": "A"
        }
      ],
      "title": "Inference Error Rate",
      "type": "timeseries"
    },
    {
      "collapsed": false,
      "gridPos": { "h": 1, "w": 24, "x": 0, "y": 14 },
      "id": 11,
      "panels": [],
      "title": "Network & Chain",
      "type": "row"
    },
    {
      "datasource": { "type": "prometheus", "uid": "${DS_PROMETHEUS}" },
      "fieldConfig": {
        "defaults": {
          "color": { "mode": "thresholds" },
          "thresholds": {
            "mode": "absolute",
            "steps": [
              { "color": "red", "value": null },
              { "color": "green", "value": 1 }
            ]
          },
          "unit": "none"
        },
        "overrides": []
      },
      "gridPos": { "h": 4, "w": 6, "x": 0, "y": 15 },
      "id": 12,
      "options": {
        "colorMode": "background",
        "graphMode": "none",
        "justifyMode": "center",
        "orientation": "auto",
        "reduceOptions": { "calcs": ["lastNotNull"], "fields": "", "values": false },
        "textMode": "auto"
      },
      "targets": [
        {
          "datasource": { "type": "prometheus", "uid": "${DS_PROMETHEUS}" },
          "expr": "xergon_agent_chain_sync_height",
          "refId": "A"
        }
      ],
      "title": "Chain Height",
      "type": "stat"
    },
    {
      "datasource": { "type": "prometheus", "uid": "${DS_PROMETHEUS}" },
      "fieldConfig": {
        "defaults": {
          "color": { "mode": "thresholds" },
          "thresholds": {
            "mode": "absolute",
            "steps": [
              { "color": "red", "value": null },
              { "color": "yellow", "value": 3 },
              { "color": "green", "value": 10 }
            ]
          },
          "unit": "none"
        },
        "overrides": []
      },
      "gridPos": { "h": 4, "w": 6, "x": 6, "y": 15 },
      "id": 13,
      "options": {
        "colorMode": "background",
        "graphMode": "none",
        "justifyMode": "center",
        "orientation": "auto",
        "reduceOptions": { "calcs": ["lastNotNull"], "fields": "", "values": false },
        "textMode": "auto"
      },
      "targets": [
        {
          "datasource": { "type": "prometheus", "uid": "${DS_PROMETHEUS}" },
          "expr": "xergon_agent_chain_node_peers",
          "refId": "A"
        }
      ],
      "title": "Node Peers",
      "type": "stat"
    },
    {
      "datasource": { "type": "prometheus", "uid": "${DS_PROMETHEUS}" },
      "fieldConfig": {
        "defaults": {
          "color": { "mode": "thresholds" },
          "thresholds": {
            "mode": "absolute",
            "steps": [
              { "color": "yellow", "value": null },
              { "color": "green", "value": 5 }
            ]
          },
          "unit": "none"
        },
        "overrides": []
      },
      "gridPos": { "h": 4, "w": 6, "x": 12, "y": 15 },
      "id": 14,
      "options": {
        "colorMode": "background",
        "graphMode": "none",
        "justifyMode": "center",
        "orientation": "auto",
        "reduceOptions": { "calcs": ["lastNotNull"], "fields": "", "values": false },
        "textMode": "auto"
      },
      "targets": [
        {
          "datasource": { "type": "prometheus", "uid": "${DS_PROMETHEUS}" },
          "expr": "xergon_p2p_peers_known",
          "refId": "A"
        }
      ],
      "title": "P2P Peers",
      "type": "stat"
    },
    {
      "datasource": { "type": "prometheus", "uid": "${DS_PROMETHEUS}" },
      "fieldConfig": {
        "defaults": {
          "color": { "mode": "thresholds" },
          "thresholds": {
            "mode": "absolute",
            "steps": [
              { "color": "red", "value": null },
              { "color": "green", "value": 1 }
            ]
          },
          "unit": "none"
        },
        "overrides": []
      },
      "gridPos": { "h": 4, "w": 6, "x": 18, "y": 15 },
      "id": 15,
      "options": {
        "colorMode": "background",
        "graphMode": "none",
        "justifyMode": "center",
        "orientation": "auto",
        "reduceOptions": { "calcs": ["lastNotNull"], "fields": "", "values": false },
        "textMode": "auto"
      },
      "targets": [
        {
          "datasource": { "type": "prometheus", "uid": "${DS_PROMETHEUS}" },
          "expr": "xergon_agent_relay_connections",
          "refId": "A"
        }
      ],
      "title": "Connected Relays",
      "type": "stat"
    },
    {
      "collapsed": false,
      "gridPos": { "h": 1, "w": 24, "x": 0, "y": 19 },
      "id": 16,
      "panels": [],
      "title": "Relay",
      "type": "row"
    },
    {
      "datasource": { "type": "prometheus", "uid": "${DS_PROMETHEUS}" },
      "fieldConfig": {
        "defaults": {
          "color": { "mode": "palette-classic" },
          "unit": "reqps"
        },
        "overrides": []
      },
      "gridPos": { "h": 8, "w": 6, "x": 0, "y": 20 },
      "id": 17,
      "options": {
        "legend": { "calcs": [], "displayMode": "list", "placement": "bottom" },
        "tooltip": { "mode": "multi", "sort": "none" }
      },
      "targets": [
        {
          "datasource": { "type": "prometheus", "uid": "${DS_PROMETHEUS}" },
          "expr": "rate(xergon_relay_requests_total{endpoint=\"chat\"}[5m])",
          "legendFormat": "chat/s",
          "refId": "A"
        }
      ],
      "title": "Chat Requests",
      "type": "timeseries"
    },
    {
      "datasource": { "type": "prometheus", "uid": "${DS_PROMETHEUS}" },
      "fieldConfig": {
        "defaults": {
          "color": { "mode": "thresholds" },
          "thresholds": {
            "mode": "absolute",
            "steps": [
              { "color": "red", "value": null },
              { "color": "green", "value": 1 }
            ]
          },
          "unit": "none"
        },
        "overrides": []
      },
      "gridPos": { "h": 8, "w": 6, "x": 6, "y": 20 },
      "id": 18,
      "options": {
        "colorMode": "background",
        "graphMode": "area",
        "justifyMode": "center",
        "orientation": "auto",
        "reduceOptions": { "calcs": ["lastNotNull"], "fields": "", "values": false },
        "textMode": "auto"
      },
      "targets": [
        {
          "datasource": { "type": "prometheus", "uid": "${DS_PROMETHEUS}" },
          "expr": "xergon_relay_providers_active",
          "refId": "A"
        }
      ],
      "title": "Active Providers",
      "type": "stat"
    },
    {
      "datasource": { "type": "prometheus", "uid": "${DS_PROMETHEUS}" },
      "fieldConfig": {
        "defaults": {
          "color": { "mode": "thresholds" },
          "thresholds": {
            "mode": "absolute",
            "steps": [
              { "color": "green", "value": null }
            ]
          },
          "unit": "none"
        },
        "overrides": []
      },
      "gridPos": { "h": 8, "w": 6, "x": 12, "y": 20 },
      "id": 19,
      "options": {
        "colorMode": "background",
        "graphMode": "none",
        "justifyMode": "center",
        "orientation": "auto",
        "reduceOptions": { "calcs": ["lastNotNull"], "fields": "", "values": false },
        "textMode": "auto"
      },
      "targets": [
        {
          "datasource": { "type": "prometheus", "uid": "${DS_PROMETHEUS}" },
          "expr": "xergon_relay_providers_total",
          "refId": "A"
        }
      ],
      "title": "Total Providers",
      "type": "stat"
    },
    {
      "datasource": { "type": "prometheus", "uid": "${DS_PROMETHEUS}" },
      "fieldConfig": {
        "defaults": {
          "color": { "mode": "thresholds" },
          "thresholds": {
            "mode": "absolute",
            "steps": [
              { "color": "green", "value": null },
              { "color": "yellow", "value": 5000 },
              { "color": "red", "value": 15000 }
            ]
          },
          "unit": "ms"
        },
        "overrides": []
      },
      "gridPos": { "h": 8, "w": 6, "x": 18, "y": 20 },
      "id": 20,
      "options": {
        "colorMode": "background",
        "graphMode": "area",
        "justifyMode": "center",
        "orientation": "auto",
        "reduceOptions": { "calcs": ["lastNotNull"], "fields": "", "values": false },
        "textMode": "auto"
      },
      "targets": [
        {
          "datasource": { "type": "prometheus", "uid": "${DS_PROMETHEUS}" },
          "expr": "xergon_relay_avg_latency_ms",
          "refId": "A"
        }
      ],
      "title": "Relay Latency",
      "type": "stat"
    },
    {
      "collapsed": false,
      "gridPos": { "h": 1, "w": 24, "x": 0, "y": 28 },
      "id": 21,
      "panels": [],
      "title": "Financial",
      "type": "row"
    },
    {
      "datasource": { "type": "prometheus", "uid": "${DS_PROMETHEUS}" },
      "fieldConfig": {
        "defaults": {
          "color": { "mode": "thresholds" },
          "thresholds": {
            "mode": "absolute",
            "steps": [
              { "color": "purple", "value": null }
            ]
          },
          "unit": "ERG"
        },
        "overrides": []
      },
      "gridPos": { "h": 4, "w": 6, "x": 0, "y": 29 },
      "id": 22,
      "options": {
        "colorMode": "background",
        "graphMode": "none",
        "justifyMode": "center",
        "orientation": "auto",
        "reduceOptions": { "calcs": ["lastNotNull"], "fields": "", "values": false },
        "textMode": "auto"
      },
      "targets": [
        {
          "datasource": { "type": "prometheus", "uid": "${DS_PROMETHEUS}" },
          "expr": "xergon_settlement_earned_erg_total",
          "refId": "A"
        }
      ],
      "title": "ERG Earned",
      "type": "stat"
    },
    {
      "datasource": { "type": "prometheus", "uid": "${DS_PROMETHEUS}" },
      "fieldConfig": {
        "defaults": {
          "color": { "mode": "thresholds" },
          "thresholds": {
            "mode": "absolute",
            "steps": [
              { "color": "red", "value": null },
              { "color": "green", "value": 1 }
            ]
          },
          "unit": "ERG"
        },
        "overrides": []
      },
      "gridPos": { "h": 4, "w": 6, "x": 6, "y": 29 },
      "id": 23,
      "options": {
        "colorMode": "background",
        "graphMode": "none",
        "justifyMode": "center",
        "orientation": "auto",
        "reduceOptions": { "calcs": ["lastNotNull"], "fields": "", "values": false },
        "textMode": "auto"
      },
      "targets": [
        {
          "datasource": { "type": "prometheus", "uid": "${DS_PROMETHEUS}" },
          "expr": "xergon_agent_wallet_balance_nanoerg / 1e9",
          "refId": "A"
        }
      ],
      "title": "Wallet Balance",
      "type": "stat"
    },
    {
      "datasource": { "type": "prometheus", "uid": "${DS_PROMETHEUS}" },
      "fieldConfig": {
        "defaults": {
          "color": { "mode": "thresholds" },
          "thresholds": {
            "mode": "absolute",
            "steps": [
              { "color": "super-light-green", "value": null },
              { "color": "green", "value": 1 }
            ]
          },
          "unit": "none"
        },
        "overrides": []
      },
      "gridPos": { "h": 4, "w": 6, "x": 12, "y": 29 },
      "id": 24,
      "options": {
        "colorMode": "background",
        "graphMode": "none",
        "justifyMode": "center",
        "orientation": "auto",
        "reduceOptions": { "calcs": ["lastNotNull"], "fields": "", "values": false },
        "textMode": "auto"
      },
      "targets": [
        {
          "datasource": { "type": "prometheus", "uid": "${DS_PROMETHEUS}" },
          "expr": "xergon_gpu_rentals_active",
          "refId": "A"
        }
      ],
      "title": "GPU Rentals Active",
      "type": "stat"
    },
    {
      "datasource": { "type": "prometheus", "uid": "${DS_PROMETHEUS}" },
      "fieldConfig": {
        "defaults": {
          "color": { "mode": "thresholds" },
          "thresholds": {
            "mode": "absolute",
            "steps": [
              { "color": "blue", "value": null }
            ]
          },
          "unit": "none"
        },
        "overrides": []
      },
      "gridPos": { "h": 4, "w": 6, "x": 18, "y": 29 },
      "id": 25,
      "options": {
        "colorMode": "background",
        "graphMode": "none",
        "justifyMode": "center",
        "orientation": "auto",
        "reduceOptions": { "calcs": ["lastNotNull"], "fields": "", "values": false },
        "textMode": "auto"
      },
      "targets": [
        {
          "datasource": { "type": "prometheus", "uid": "${DS_PROMETHEUS}" },
          "expr": "xergon_rollup_commitments_total",
          "refId": "A"
        }
      ],
      "title": "Rollup Commitments",
      "type": "stat"
    },
    {
      "collapsed": false,
      "gridPos": { "h": 1, "w": 24, "x": 0, "y": 33 },
      "id": 26,
      "panels": [],
      "title": "Errors & Alerts",
      "type": "row"
    },
    {
      "datasource": { "type": "prometheus", "uid": "${DS_PROMETHEUS}" },
      "fieldConfig": {
        "defaults": {
          "color": { "mode": "palette-classic" },
          "unit": "short"
        },
        "overrides": []
      },
      "gridPos": { "h": 8, "w": 12, "x": 0, "y": 34 },
      "id": 27,
      "options": {
        "legend": { "calcs": [], "displayMode": "list", "placement": "bottom" },
        "tooltip": { "mode": "multi", "sort": "none" }
      },
      "targets": [
        {
          "datasource": { "type": "prometheus", "uid": "${DS_PROMETHEUS}" },
          "expr": "rate(xergon_agent_inference_errors_total[5m])",
          "legendFormat": "agent errors/s",
          "refId": "A"
        }
      ],
      "title": "Agent Errors",
      "type": "timeseries"
    },
    {
      "datasource": { "type": "prometheus", "uid": "${DS_PROMETHEUS}" },
      "fieldConfig": {
        "defaults": {
          "color": { "mode": "palette-classic" },
          "unit": "short"
        },
        "overrides": []
      },
      "gridPos": { "h": 8, "w": 12, "x": 12, "y": 34 },
      "id": 28,
      "options": {
        "legend": { "calcs": [], "displayMode": "list", "placement": "bottom" },
        "tooltip": { "mode": "multi", "sort": "none" }
      },
      "targets": [
        {
          "datasource": { "type": "prometheus", "uid": "${DS_PROMETHEUS}" },
          "expr": "rate(xergon_relay_errors_total[5m])",
          "legendFormat": "relay errors/s",
          "refId": "A"
        }
      ],
      "title": "Relay Errors",
      "type": "timeseries"
    }
  ],
  "refresh": "10s",
  "schemaVersion": 39,
  "tags": ["xergon", "agent", "relay", "monitoring"],
  "templating": {
    "list": [
      {
        "current": {},
        "hide": 0,
        "includeAll": false,
        "label": "Prometheus",
        "multi": false,
        "name": "DS_PROMETHEUS",
        "options": [],
        "query": "prometheus",
        "queryValue": "",
        "refresh": 1,
        "regex": "",
        "skipUrlSync": false,
        "type": "datasource"
      }
    ]
  },
  "time": { "from": "now-1h", "to": "now" },
  "timepicker": {
    "refresh_intervals": ["5s", "10s", "30s", "1m", "5m", "15m", "30m", "1h"]
  },
  "timezone": "",
  "title": "Xergon Overview",
  "uid": "xergon-overview",
  "version": 1,
  "description": "Xergon Network production monitoring dashboard"
}
